
[{"content":"","date":"21 April 2026","externalUrl":null,"permalink":"/My-Website/categories/","section":"Categories","summary":"","title":"Categories","type":"categories"},{"content":"","date":"21 April 2026","externalUrl":null,"permalink":"/My-Website/","section":"HOME","summary":"","title":"HOME","type":"page"},{"content":"","date":"21 April 2026","externalUrl":null,"permalink":"/My-Website/notes/","section":"Notes","summary":"","title":"Notes","type":"notes"},{"content":"","date":"21 April 2026","externalUrl":null,"permalink":"/My-Website/series/","section":"Series","summary":"","title":"Series","type":"series"},{"content":"","date":"21 April 2026","externalUrl":null,"permalink":"/My-Website/tags/","section":"Tags","summary":"","title":"Tags","type":"tags"},{"content":"","date":"21 April 2026","externalUrl":null,"permalink":"/My-Website/categories/%E5%AE%9F%E9%A8%93/","section":"Categories","summary":"","title":"実験","type":"categories"},{"content":"\r11タイプの屋根に対する通風実験\r#\r11タイプ:\r#\r陸屋根:厚さ（0mm, 1/4, 2/4, 3/4, 4/4） 切妻屋根:勾配(15°, 30°) 片流れ屋根:勾配(15°, 30°), 逆方向\n","date":"21 April 2026","externalUrl":null,"permalink":"/My-Website/notes/4-22-wind/","section":"Notes","summary":"風洞実験の日常記録","title":"屋根を変わる通風実験","type":"notes"},{"content":"","date":"21 April 2026","externalUrl":null,"permalink":"/My-Website/tags/%E9%80%9A%E9%A2%A8/","section":"Tags","summary":"","title":"通風","type":"tags"},{"content":"","date":"21 April 2026","externalUrl":null,"permalink":"/My-Website/tags/%E9%A2%A8%E6%B4%9E%E5%AE%9F%E9%A8%93/","section":"Tags","summary":"","title":"風洞実験","type":"tags"},{"content":"","date":"21 April 2026","externalUrl":null,"permalink":"/My-Website/series/%E9%A2%A8%E9%80%9F%E5%AE%9F%E9%A8%93%E3%82%B7%E3%83%AA%E3%83%BC%E3%82%BA/","section":"Series","summary":"","title":"風速実験シリーズ","type":"series"},{"content":"","date":"20 April 2026","externalUrl":null,"permalink":"/My-Website/tags/%E6%A0%A1%E6%AD%A3/","section":"Tags","summary":"","title":"校正","type":"tags"},{"content":"\r風洞実験の流れ\r#\r第一日　実験の下準備\r#\r朝　#\r風速計端子は中継ボックスに挿入し、センサー端は新しいテープを交換した。 使用したのは熱タイプの風速計であり、一定温度を維持する原理に基づいている。 気流によって温度が変化するため、その温度を一定に保つために必要な電圧を測定することで、風速を算出する。\n風速計をボックスに入れる\r昼\r#\r先ず、送風機の回転数(60、90、120、150、200、250 RPM)に対して、ピトー管1を用いて風速を測定した。\nベルヌーイの定理より、\n$$\r\\Delta p + \\frac{1}{2}\\rho v^2 = \\text{定数}\r$$ が成り立ち、風速は次式で求められる: $$\rv = \\sqrt{\\frac{2\\Delta p}{\\rho}}\r$$ これにより、風速と送風機回転数(RPM)との関係式 $$\rv_{\\text{ref}} = f(\\text{RPM})\r$$ を得た。\n更に、得られた風速をMass Flow Controllerを用いて、多点風速計校正プログラムというソフトに入力した。各測定点において一分間の平均電圧(18点)を取得し、風速と電圧の対応関係を求めた。その結果、精度の高い校正曲線を作成した。\nピトー管\r第二日　風洞内の設置\r#\r朝\r#\r風速計(1~16番)を板に順番に取り付け、板から垂直距離を6mmに設定した。その後、板をターンテーブルに設置した。\n風速計を取り付ける\r昼\r#\r風洞内の境界層を形成するため、ソー、スパイヤ（三基）、およびラフネス（大13列、中25列、小9列）を設置した。 これにより、べき指数0.25（=1/4）の平均風速分布を再現した。\n設置した様子\r第三日　実験開始\r#\r朝\r#\r先ず、ピトー管を用いて今日の基準風速を測定した。その後、実験用ソフトに第一日に作成した校正曲線を読み込み、測量を開始した。\n全圧と静圧の差から動圧を求め、ベルヌーイの定理に基づいて流速を算出する測定装置である。\u0026#160;\u0026#x21a9;\u0026#xfe0e;\n","date":"20 April 2026","externalUrl":null,"permalink":"/My-Website/notes/4-17-4-21-wind-tunnel/","section":"Notes","summary":"風洞実験の日常記録、風速計の校正作業について","title":"風速実験の日常","type":"notes"},{"content":"","date":"20 April 2026","externalUrl":null,"permalink":"/My-Website/tags/%E9%A2%A8%E9%80%9F%E8%A8%88/","section":"Tags","summary":"","title":"風速計","type":"tags"},{"content":"\r2D模拟求解器总结\r#\r第一部分 破题\r#\r观点\r#\r学了什么\r#\r第二部分 演进\r#\r阶段一 一维基础\r#\r阶段二 二维基础\r#\r阶段三 解决N-S方程的核心 压力泊松方程\r#\r第三部分 成果展示与对比\r#\r配图\r#\r技术深度\r#\r思考\r#\r","externalUrl":null,"permalink":"/My-Website/portfolios/ex/","section":"Portfolios","summary":"","title":"","type":"portfolios"},{"content":"","externalUrl":null,"permalink":"/My-Website/authors/","section":"Authors","summary":"","title":"Authors","type":"authors"},{"content":"","externalUrl":null,"permalink":"/My-Website/portfolios/","section":"Portfolios","summary":"","title":"Portfolios","type":"portfolios"}]